otf_abfe/.DS_Store
otf_abfe/README.md
otf_abfe/__init__.py
otf_abfe/abfe_all_prep.sh
otf_abfe/abfe_main.py
otf_abfe/abfe_simulate.py
otf_abfe/analysis/analysis.py
otf_abfe/analysis/analysis.sh
otf_abfe/analysis/compile_analysis.py
otf_abfe/auto_restraint_files/.ipynb_checkpoints/restraint_analysis-checkpoint.py
otf_abfe/auto_restraint_files/README.md
otf_abfe/auto_restraint_files/auto_restraint.sh
otf_abfe/auto_restraint_files/cpptraj.restraint.sh
otf_abfe/auto_restraint_files/restraint_analysis.py
otf_abfe/auto_restraint_files/restraint_analysis_functions.py
otf_abfe/dcrg+vdw/1_min/1min.in
otf_abfe/dcrg+vdw/1_min/2min.in
otf_abfe/dcrg+vdw/2_nvt/nvt.in
otf_abfe/dcrg+vdw/3_npt/1_npt.in
otf_abfe/dcrg+vdw/3_npt/2_npt.in
otf_abfe/dcrg+vdw/3_npt/3_npt.in
otf_abfe/dcrg+vdw/md-lambda.sh
otf_abfe/dcrg+vdw/prod/prod.in
otf_abfe/dcrg+vdw/prod/restart.in
otf_abfe/dcrg+vdw/restart.sh
otf_abfe/parameterization/all-check-done.sh
otf_abfe/parameterization/all-prep-lig-g09.sh
otf_abfe/parameterization/all-prep-lig-g16.sh
otf_abfe/parameterization/input-for-prep/cpp.strip-wat.in
otf_abfe/parameterization/input-for-prep/tleap.complex.in
otf_abfe/parameterization/input-for-prep/tleap.lig_ac.in
otf_abfe/parameterization/input-for-prep/tleap.ligwat.in
otf_abfe/parameterization/prep-lig-resp-g09.sh
otf_abfe/parameterization/prep-lig-resp-g16.sh
otf_abfe/rtr/md-lambda.sh
otf_abfe/rtr/prod/prod.in
otf_abfe/rtr/prod/restart.in
otf_abfe/rtr/restart.sh
otf_abfe/run_abfe.sh
otf_abfe/template.cpp.get-vb.in
otf_abfe/water-dcrg+vdw/1_min/1min.in
otf_abfe/water-dcrg+vdw/1_min/2min.in
otf_abfe/water-dcrg+vdw/2_nvt/nvt.in
otf_abfe/water-dcrg+vdw/3_npt/1_npt.in
otf_abfe/water-dcrg+vdw/3_npt/2_npt.in
otf_abfe/water-dcrg+vdw/3_npt/3_npt.in
otf_abfe/water-dcrg+vdw/md-equil.sh
otf_abfe/water-dcrg+vdw/prod/prod.in
otf_abfe/water-dcrg+vdw/prod/restart.in
otf_abfe/water-dcrg+vdw/restart.sh
otf_rbfe/.DS_Store
otf_rbfe/README.md
otf_rbfe/__init__.py
otf_rbfe/analysis/analysis_gt.py
otf_general-0.1.0.dist-info/LICENSE
otf_general-0.1.0.dist-info/METADATA
otf_general-0.1.0.dist-info/WHEEL
otf_general-0.1.0.dist-info/RECORD
