Metadata-Version: 2.3
Name: OTF_General
Version: 0.1.0
Summary: Alchemical binding free‐energy workflow
License: MIT
Author: S. Benjamin Koby and Maria G. Kurnikova
Requires-Python: >=3.12
Classifier: License :: OSI Approved :: MIT License
Classifier: Programming Language :: Python :: 3
Classifier: Programming Language :: Python :: 3.12
Classifier: Programming Language :: Python :: 3.13
Requires-Dist: numpy (>=2.3.2,<3.0.0)
